Workbook

Sheet GP_DSA_ranges
A1: Input | B1: Low | C1: High | D1: Not in use anymore
A2: smd_1 | B2: -1.13 | C2: 0.13
A3: smd_2 | B3: -1.29 | C3: -0.05
A4: smd_3 | B4: -1.61 | C4: 0.35
A5: smd_sat | B5: 0.33 | C5: 1.33
A6: n_patients_eligible | B6: 22831200 | C6: 16476124
A7: p_subgroup1 | B7: 0.384 | C7: 0.486
A8: p_subgroup2 | B8: 0.24464 | C8: 0.36696
A9: p_subgroup3 | B9: 0.18144 | C9: 0.27216
A10: n_providers | B10: 28249 | C10: 28249
A11: v_threshold_1 | B11: 1 | C11: 1
A12: v_threshold_2 | B12: 12 | C12: 12
A13: v_threshold_3 | B13: 12 | C13: 12
A14: v_mean_1_int
A15: v_mean_2_int
A16: v_mean_3_int
A17: v_mean_1_ctrl | B17: 2 | C17: 3
A18: v_mean_2_ctrl | B18: 17.36 | C18: 26.04
A19: v_mean_3_ctrl | B19: 22.32 | C19: 33.48
A20: sd_1
A21: sd_2
A22: sd_3
A23: c_training_online | B23: 2.48 | C23: 3.72
A24: c_training_f2f | B24: 11.68 | C24: 17.52
A25: v_training_hours_online | B25: 5 | C25: 5
A26: v_training_hours_f2f | B26: 7 | C26: 7
A27: n_training_sessions | B27: 0 | C27: 0
A28: c_opp_provider_hourly | B28: 128.8 | C28: 193.2
A29: c_offset_1 | B29: 155.2 | C29: 232.8
A30: c_offset_2 | B30: 5182.88 | C30: 7774.32
A31: c_offset_3 | B31: 9001.904 | C31: 13502.856
A32: c_care_component1_per_unit | B32: 3.576 | C32: 5.364
A33: n_care_component1_units | B33: 2 | C33: 2
A34: c_care_component2_per_unit
A35: n_care_component2_units
A36: p_satisfaction_int
A37: p_satisfaction_ctrl | B37: 0.5704 | C37: 0.8556
A38: p_burnout_ctrl | B38: 0.284 | C38: 0.426
A39: rr_burnout | B39: 0.72 | C39: 1.08
A40: c_offset_burnout | B40: 4499.2 | C40: 6748.8

Sheet GP_full
A1: For_R | B1: Input | C1: Value | D1: Mean | E1: SD | F1: DSA_low | G1: DSA_high | H1: PSA_dis | I1: PSA_param1 | J1: PSA_param2 | K1: Description | L1: Label_R | M1: Link | N1: Details from Ref | O1: Currency | P1: price_year_original | Q1: category_for_index | R1: value_inflated | S1: Source_index
K2: From a meta-analysis
A3: 1 | B3: smd_1 | C3: =D3 -> -0.5 | D3: -0.5 | E3: =(G3-C3)/1.96 -> 0.32142857 | F3: -1.13 | G3: 0.13 | H3: normal | I3: =C3 -> -0.5 | J3: =E3 -> 0.32142857 | K3: SMD_pain | L3: Effect size on pain | N3: SMD=-0.5, 95%CI: -1.13, 0.13, N_intervention:291, N_control = 287
A4: 1 | B4: smd_2 | C4: =D4 -> -0.67 | D4: -0.67 | E4: =(G4-C4)/1.96 -> 0.31632653 | F4: -1.29 | G4: -0.05 | H4: normal | I4: =C4 -> -0.67 | J4: =E4 -> 0.31632653 | K4: SMD_anxiety | L4: Effect size on anxiety | N4: SMD=-0.67, 95%CI: -1.29, -0.05, N_intervention:780, N_control = 1076
A5: 1 | B5: smd_3 | C5: =D5 -> -0.63 | D5: -0.63 | E5: =(G5-C5)/1.96 -> 0.5 | F5: -1.61 | G5: 0.35 | H5: normal | I5: =C5 -> -0.63 | J5: =E5 -> 0.5 | K5: SMD_depression | L5: Effect size on depression | N5: SMD=-0.63, 95%CI: -1.61, 0.35, N_intervention:548, N_control = 562
A6: 1 | B6: smd_sat | C6: =D6 -> 0.98 | D6: 0.98 | E6: =(G6-C6)/1.96 -> 0.26020408 | F6: 0.46 | G6: 1.49 | H6: normal | I6: =C6 -> 0.98 | J6: =E6 -> 0.26020408 | K6: SMD_satisfaction | L6: Effect size on satisfaction | N6: SMD=0.98, 95%CI: 0.46, 1.49. N_intervention:875, N_control = 619
F7: 0.8 | G7: 1.2 | K7: From literature & calculation
B8: n_patients_eligible | C8: =D8 -> 19255229 | D8: =ROUND(D9/D10,0) -> 19255229 | F8: =ROUND(F9/F10,0) -> 22831200 | G8: =ROUND(G9/G10,0) -> 16476124
A9: 1 | B9: n_pt_compo1 | C9: =D9 -> 159818400 | D9: =30.2*10^6*12*44.1% -> 159818400 | F9: =D9 -> 159818400 | G9: =D9 -> 159818400 | K9: Total number of GP consultations per year | L9: Number of GP consulations annually | M9: https://digital.nhs.uk/data-and-information/publications/statistical/appointments-in-general-practice/april-2025 | N9: 30.2m appointments were recorded across General Practice in England in April 2025 (we assume this is a monthly number), 44.1% of all appointments in April 2025 were carried out by a GP
A10: 1 | B10: n_pt_compo2 | C10: =D10 -> 8.3 | D10: 8.3 | E10: =(G10-C10)/1.96 -> 0.71428571 | F10: 7 | G10: 9.7 | H10: normal | I10: =C10 -> 8.3 | J10: =E10 -> 0.71428571 | K10: Total number of GP visits per patient per year | L10: Number of GP visits per patient annually | M10: https://bmjopen.bmj.com/content/11/12/e054666 | N10: 8.3 (7.0–9.7) GP consultation per acitive patients in 2018–2019 (Table 1)
A11: 2 | B11: formula_n_patients | C11: =D11 -> n_compo1/n_compo2 | D11: n_compo1/n_compo2
A12: 1 | B12: p_subgroup1 | C12: =D12 -> 0.435 | D12: 0.435 | E12: =(G12-C12)/1.96 -> 0.026020408 | F12: 0.384 | G12: 0.486 | H12: beta | I12: =C12*(((C12*(1-C12))/E12^2)-1) -> 157.47104 | J12: =(1-C12)*(((C12*(1-C12))/E12^2)-1) -> 204.53136 | K12: Population-based prevalence estimates of chronic pain | L12: Chronic pain prevalence | M12: https://pmc.ncbi.nlm.nih.gov/articles/PMC4932255/ | N12: The prevalence of chronic pain, derived from 7 studies, ranged from 35.0% to 51.3% (pooled estimate 43.5%, 95% CIs 38.4% to 48.6%)
D13: 0.34 | K13: % of chronic pain in adults 2017 Health Survey for England | M13: https://assets.publishing.service.gov.uk/media/5fc8c6b78fa8f547585ed7f3/Chronic_Pain_Report.pdf | N13: 34% of respondents reported some level of chronic pain which was unchanged from 2011
A14: 1 | B14: p_subgroup2 | C14: =D15 -> 0.072 | D14: 0.3058 | E14: =(0.072-0.071)/(2*1.96) -> 0.00025510204 | F14: =C14-1.96*E14 -> 0.0715 | G14: =C14+1.96*E14 -> 0.0725 | H14: beta | I14: =C14*(((C14*(1-C14))/E14^2)-1) -> 73923.868 | J14: =(1-C14)*(((C14*(1-C14))/E14^2)-1) -> 952796.51 | K14: prevalence of anxiety | L14: Anxiety prevalence | M14: McDaid 2022 | N14: ﻿Table 3 - Prevalence of mental disorders in the UK in 2019: Anxiety 30.58% (all ages)
D15: 0.072 | K15: Prevalence of anxiety in primary care in England | M15: https://academic.oup.com/fampra/article-abstract/27/1/9/478534?redirectedFrom=fulltext | N15: The overall prevalence of anxiety was 7.2% (95% CI: 7.1–7.2)
A16: 1 | B16: p_subgroup3 | C16: =D17 -> 0.0838 | D16: 0.2268 | E16: =(0.098-0.0704)/1.349 -> 0.0204596 | F16: =C16-1.96*E16 -> 0.043699185 | G16: =C16+1.96*E16 -> 0.12390082 | H16: beta | I16: =C16*(((C16*(1-C16))/E16^2)-1) -> 15.286561 | J16: =(1-C16)*(((C16*(1-C16))/E16^2)-1) -> 167.13063 | K16: prevalence of depresison | L16: Depression prevalence | M16: McDaid 2022 | N16: ﻿Table 3 - Prevalence of mental disorders in the UK in 2019: Depression 22.68% (all ages)
D17: 0.0838 | K17: Prevalence of depresson in primary care in England | M17: https://pmc.ncbi.nlm.nih.gov/articles/PMC7083582/#sec3 | N17: "Based on practice registers, mean % prevalence of depression ... for 2015–2016 were 8.38 (median: 8.21, IQR: 7.04–9.80),…"
A18: 1 | B18: n_providers | C18: =D19 -> 28249 | D18: 38018 | F18: =C18 -> 28249 | G18: =C18 -> 28249 | K18: Total number of full-time GPs | L18: Number of GPs | M18: https://digital.nhs.uk/data-and-information/publications/statistical/general-and-personal-medical-services/31-may-2025 | N18: 38,018 FTE GPs
D19: 28249 | K19: Total number of full-time fully qualified GPs | M19: https://digital.nhs.uk/data-and-information/publications/statistical/general-and-personal-medical-services/31-may-2025 | N19: 28,249 FTE Fully qualified GPs (excludes GPs in Training Grade)
B20: n_provider_compo1
B21: n_provider_compo2
B22: formula_n_providers
A23: 1 | B23: v_threshold_1 | C23: =D23 -> 1 | D23: 1 | F23: =C23 -> 1 | G23: =C23 -> 1 | K23: threshold of pain score | L23: Pain threshold | M23: https://bmjopen.bmj.com/content/13/11/e073096.long#DC1 | N23: Chronic pain episodes that did not require substantial intervention from the healthcare system, and thereby did not comprise a moderate-to-severe pain event, were classified as mild chronic pain
A24: 1 | B24: v_threshold_2 | C24: =D24 -> 12 | D24: 12 | F24: =D24 -> 12 | G24: =D24 -> 12 | K24: threshold of CIS-R score for patients with anxiety | L24: Anxiety threshold | N24: See the APMS 2023/4 Methods documentation for a description of the CIS-R. A score of 12 indicates a level of common mental health symptoms that is likely to benefit from clinical recognition.
A25: 1 | B25: v_threshold_3 | C25: =D25 -> 12 | D25: 12 | F25: =D25 -> 12 | G25: =D25 -> 12 | K25: threshold of CIS-R score for patients with depression | L25: Depression threshold
B26: v_mean_1_int | C26: =D26 -> 2.1 | D26: =ROUND(D29+D3*E29,2) -> 2.1 | E26: =E29 -> 0.809 | K26: Mean pain score scale 0-3 of the population under empathic care | M26: Calculation | N26: Assuming SD_ctrl = SD_int => SD_pooled = SD_ctrl => mean_int=mean_ctrl+SD_ctrl*SMD
B27: v_mean_2_int | C27: =D27 -> 12.77 | D27: =ROUND(D30+D4*E30,2) -> 12.77 | E27: =E30 -> 13.331 | K27: Mean CIS-R score of patients with anxiety under empathic care | M27: Calculation | N27: Assuming SD_ctrl = SD_int => SD_pooled = SD_ctrl => mean_int=mean_ctrl+SD_ctrl*SMD
B28: v_mean_3_int | C28: =D28 -> 18.72 | D28: =ROUND(D31+D5*E31,2) -> 18.72 | E28: =E31 -> 14.566 | K28: Mean CIS-R score of patients with depression under empathic care | M28: Calculation | N28: Assuming SD_ctrl = SD_int => SD_pooled = SD_ctrl => mean_int=mean_ctrl+SD_ctrl*SMD
A29: 1 | B29: v_mean_1_ctrl | C29: =D29 -> 2.5 | D29: =ROUND(0.202*1+0.097*2+0.701*3,2) -> 2.5 | E29: =ROUND(SQRT(0.202*(1 - 2.499)^2 + 0.097*(2 - 2.499)^2 + 0.701*(3 - 2.499)^2),3) -> 0.809 | F29: =C29*$F$7 -> 2 | G29: =C29*$G$7 -> 3 | H29: normal | I29: =C29 -> 2.5 | J29: =E29 -> 0.809 | K29: Mean pain score scale 0-3 | L29: Pain score under usual care | M29: https://bmjopen.bmj.com/content/13/11/e073096.long#DC1 | N29: Among cases, at index 4649 patients (20.2%) had mild pain, 2227 (9.7%) had moderate pain and 16 140 (70.1%) had severe pain. (we transform the pain level from categorical to continuous scale (mild-1, moderate-2, severe-3
A30: 1 | B30: v_mean_2_ctrl | C30: =D30 -> 21.7 | D30: 21.7 | E30: =ROUND(0.57*SQRT(547),3) -> 13.331 | F30: =C30*$F$7 -> 17.36 | G30: =C30*$G$7 -> 26.04 | H30: normal | I30: =C30 -> 21.7 | J30: =E30 -> 13.331 | K30: Mean CIS-R score of patients with anxiety under standard of care | L30: Anxiety score under usual care | M30: https://digital.nhs.uk/data-and-information/publications/statistical/adult-psychiatric-morbidity-survey/survey-of-mental-health-and-wellbeing-england-2023-24/mental-health-treatment-and-service-use | N30: Patients with Generalised anxiety disorder: Mean CIS-R score = 21.7, SE = 0.57, N=547 (Table 2.4)
A31: 1 | B31: v_mean_3_ctrl | C31: =D31 -> 27.9 | D31: 27.9 | E31: =ROUND(0.83*SQRT(308),3) -> 14.566 | F31: =C31*$F$7 -> 22.32 | G31: =C31*$G$7 -> 33.48 | H31: normal | I31: =C31 -> 27.9 | J31: =E31 -> 14.566 | K31: Mean CIS-R score of patients with depression under standard of care | L31: Depression score under usual care | M31: https://digital.nhs.uk/data-and-information/publications/statistical/adult-psychiatric-morbidity-survey/survey-of-mental-health-and-wellbeing-england-2023-24/mental-health-treatment-and-service-use | N31: Patients with Depressive episode: Mean CIS-R score = 27.9, SE = 0.83, N=308 (Table 2.4)
A32: 1 | B32: sd_1 | C32: =E32 -> 0.809 | E32: 0.809 | F32: =C32*$F$7 -> 0.6472 | G32: =C32*$G$7 -> 0.9708 | L32: Standard deviation of pain score
A33: 1 | B33: sd_2 | C33: =E33 -> 13.331 | E33: 13.331 | F33: =C33*$F$7 -> 10.6648 | G33: =C33*$G$7 -> 15.9972 | L33: Standard deviation of anxiety score
A34: 1 | B34: sd_3 | C34: =E34 -> 14.566 | E34: 14.566 | F34: =C34*$F$7 -> 11.6528 | G34: =C34*$G$7 -> 17.4792 | L34: Standard deviation of depression score
A35: 1 | B35: c_training_online | C35: =D35 -> 3.1 | D35: 3.1 | E35: =(G35-C35)/1.96 -> 0.31632653 | F35: =C35*$F$7 -> 2.48 | G35: =C35*$G$7 -> 3.72 | H35: gamma | I35: =C35^2/E35^2 -> 96.04 | J35: =E35^2/C35 -> 0.032278217 | K35: Cost of online training per GP | L35: Training online cost | N35: Expert facilitator (1): 200; Training for facilitator: 10; Admin support (1/2 day): 100; Resources 0; Lunch + refreshments 0; Total_cost: 310 Cost per HCP: 3.1
A36: 1 | B36: c_training_f2f | C36: =D36 -> 14.6 | D36: 14.6 | E36: =(G36-C36)/1.96 -> 1.4897959 | F36: =C36*$F$7 -> 11.68 | G36: =C36*$G$7 -> 17.52 | H36: gamma | I36: =C36^2/E36^2 -> 96.04 | J36: =E36^2/C36 -> 0.15201999 | K36: Cost of f2f training per GP | L36: Training offline cost | N36: Expert facilitator (1): 200; Training for facilitator: 10; Admin support (1/2 day): 100; Resources 50; Lunch + refreshments 1000; Total_cost: 1460 Cost per HCP: 14.6
A37: 1 | B37: v_training_hours_online | C37: =D37 -> 5 | D37: 5 | F37: =D37 -> 5 | G37: =D37 -> 5 | K37: Training duration for an online program | L37: Training online duration
A38: 1 | B38: v_training_hours_f2f | C38: =D38 -> 7 | D38: 7 | F38: =D38 -> 7 | G38: =D38 -> 7 | K38: Training duration for a face-to-face program | L38: Training offline duration
A39: 1 | B39: n_training_sessions | C39: =D39 -> 1 | D39: 1 | F39: =C39 -> 1 | G39: =C39 -> 1 | L39: Number of training sessions
A40: 1 | B40: c_opp_provider_hourly | C40: =D40 -> 161 | D40: 161 | E40: =(G40-C40)/1.96 -> 16.428571 | F40: =C40*$F$7 -> 128.8 | G40: =C40*$G$7 -> 193.2 | H40: gamma | I40: =C40^2/E40^2 -> 96.04 | J40: =E40^2/C40 -> 1.6763848 | K40: Opportunity cost of GPs (taking the training course instead of working) | L40: Opportunity cost of GP | M40: PSSRU 2024 | N40: Table 9.4.2. ﻿Per hour of GMS activity ﻿Including direct care staff costs - ﻿With qualification costs: 161. (﻿GMS: General Medical Service)
A41: 1 | B41: c_offset_1 | C41: =R42 -> 233 | D41: 240.3 | E41: =(G41-C41)/1.96 -> 23.77551 | F41: =C41*$F$7 -> 186.4 | G41: =C41*$G$7 -> 279.6 | H41: gamma | I41: =C41^2/E41^2 -> 96.04 | J41: =E41^2/C41 -> 2.4260725 | K41: Cost associated with reduced pain per patient | L41: Saving from reduced pain per patient | M41: https://journals.sagepub.com/doi/10.1177/2049463719865286#sec-3 | N41: The cost of health care for those who engaged in the programme was £240.30 less per patient than those who did not engage
D42: =256-62 -> 194 | M42: https://bmjopen.bmj.com/content/13/11/e073096.long#DC1 | N42: In the first 12 months postindexing, mean total costs incurred by cases were four times higher versus matched controls (£256 vs £62). Cost year: 2019 | O42: £ | P42: 2019 | Q42: NHSII pay and prices | R42: {=ROUND(D42*PRODUCT(1+NHSII!D8:D12),0)} -> 233 | S42: PSSRU 2024
A43: 1 | B43: c_offset_2 | C43: =R43 -> 7788 | D43: =ROUND(20406*10^6/(10.3*10^6*0.3058),1) -> 6478.6 | E43: =(G43-C43)/1.96 -> 794.69388 | F43: =C43*$F$7 -> 6230.4 | G43: =C43*$G$7 -> 9345.6 | H43: gamma | I43: =C43^2/E43^2 -> 96.04 | J43: =E43^2/C43 -> 81.091212 | K43: Cost associated with improved anxiety per patient | L43: Saving from improved anxiety per patient | M43: McDaid 2022 | N43: ﻿Table 6-Annual cost by mental health condition, UK, 2019 (£ millions): anxiety 20,406 (total UK); ﻿10.3 million cases of mental health conditions, prevalence 30.58% | O43: £ | P43: 2019 | Q43: NHSII pay and prices | R43: {=ROUND(D43*PRODUCT(1+NHSII!D8:D12),0)} -> 7788 | S43: PSSRU 2024
A44: 1 | B44: c_offset_3 | C44: =R44 -> 13527 | D44: =26286*10^6/(10.3*10^6*0.2268) -> 11252.376 | E44: =(G44-C44)/1.96 -> 1380.3061 | F44: =C44*$F$7 -> 10821.6 | G44: =C44*$G$7 -> 16232.4 | H44: gamma | I44: =C44^2/E44^2 -> 96.04 | J44: =E44^2/C44 -> 140.84756 | K44: Cost associated with improved depression per patient | L44: Saving from improved depression per patient | M44: McDaid 2022 | N44: ﻿Table 6-Annual cost by mental health condition, UK, 2019 (£ millions): anxiety ﻿26,286 (total UK). 10.3 million cases of mental health conditions, prevalence 22.68% | O44: £ | P44: 2019 | Q44: NHSII pay and prices | R44: {=ROUND(D44*PRODUCT(1+NHSII!D8:D12),0)} -> 13527 | S44: PSSRU 2024
A45: 1 | B45: c_care_component1_per_unit | C45: =D45 -> 4.47 | D45: 4.47 | E45: =(G45-C45)/1.96 -> 0.45612245 | F45: =C45*$F$7 -> 3.576 | G45: =C45*$G$7 -> 5.364 | H45: gamma | I45: =C45^2/E45^2 -> 96.04 | J45: =E45^2/C45 -> 0.046543107 | K45: Cost associated with extended consultation duration per minutes | L45: Cost of extending consultation | M45: https://www.pssru.ac.uk/unitcostsreport/ | N45: Table 9.4.2. Unit cost 2023/2024 ﻿Per minute of patient contact £4.47
A46: 1 | B46: n_care_component1_units | C46: =D46 -> 2 | D46: 2 | F46: =C46 -> 2 | G46: =C46 -> 2 | K46: Extened duration (in munites) | L46: Extended consultation duration | M46: Assumption
B47: c_care_component2_per_unit | C47: NA
B48: n_care_component2_units | C48: NA
B49: p_satisfaction_int | C49: =ROUND(D49,2) -> 0.94 | D49: =_xlfn.NORM.S.DIST(_xlfn.NORM.S.INV(D50)+D6,TRUE) -> 0.93848389 | K49: Proportion of patients satisfied with the empathic care at GP | M49: Calculation | N49: To estimate the intervention group satisfaction rate from a known control group satisfaction rate and SMD, assume satisfaction is determined by a latent standard normal variable. The control group’s satisfaction rate defines a threshold on this latent scale. The SMD shifts the mean of this distribution, and the resulting cumulative probability gives the intervention group’s expected satisfaction rate.
A50: 1 | B50: p_satisfaction_ctrl | C50: =D50 -> 0.713 | D50: 0.713 | E50: =(G50-C50)/1.96 -> 0.072755102 | F50: =C50*$F$7 -> 0.5704 | G50: =C50*$G$7 -> 0.8556 | H50: beta | I50: =C50*(((C50*(1-C50))/E50^2)-1) -> 26.85048 | J50: =(1-C50)*(((C50*(1-C50))/E50^2)-1) -> 10.807977 | K50: Proportion of patients satisfied with the standard of care at GP | L50: Satisfaction rate under usual care | M50: https://gp-patient.co.uk/downloads/2023/GPPS_2023_National_report_PUBLIC.pdf | N50: 71.3% of patients rated their overall experience of their GP practice as good
A51: 1 | B51: d_absent_per_hcp | C51: =ROUND(D51,2) -> 1.15 | D51: =151329/132113 -> 1.1454512 | K51: Number of absent days due to burnout among GPs annually | L51: Days absent per GP | M51: IPPO report (ref 42 burnout | N51: Table 3: Days absent due to mental health, in Doctors: 151329; number of Doctors: 132,113
A52: 1 | B52: c_hcp_day_rate | C52: =R52 -> 365 | D52: 314.76 | K52: Cost of an absent day | L52: Day wage per GP | M52: IPPO report (ref 42 burnout | N52: Table 3: FTE daily rate of Doctors | O52: £ | P52: 2022 | Q52: NHSII pay | R52: {=ROUND(D52*PRODUCT(1+NHSII!C10:C12),0)} -> 365 | S52: PSSRU 2024
A53: 1 | B53: r_absent_reduct | C53: =D53 -> 0.1 | D53: 0.1 | K53: Percentage reduction in absent days due to the intervention | L53: Reduction rate in absent days under intervention | M53: Assumption
A54: 1 | B54: n_complaints | C54: =D54 -> 113041 | D54: 113041 | K54: Number of written complaints in GP 2023/2024 | L54: Number of complaints | M54: https://digital.nhs.uk/data-and-information/publications/statistical/data-on-written-complaints-in-the-nhs/2023-24 | N54: Table 5 data file of written complaints 2023/2024: the numer of complaints in GP is 113041
A55: 1 | B55: c_complaint | C55: =R55 -> 1001.33 | D55: 667.17 | E55: =(G55-C55)/1.96 -> 102.17653 | F55: =C55*$F$7 -> 801.064 | G55: =C55*$G$7 -> 1201.596 | H55: gamma | I55: =C55^2/E55^2 -> 96.04 | J55: =E55^2/C55 -> 10.426177 | K55: Cost associated with reducing one complaint | L55: Cost per complaint | M55: National audit office report 2008 | N55: "﻿﻿﻿In 2006-07, The estimated cost of handling and review of NHS complaints was £89 million" "﻿The NHS Received 133,400 written complaints" => cost per complaint: =89e6/133400=677 | O55: £ | P55: 2006 | Q55: NHSII pay and prices | R55: {=ROUND(D55*NHSII!N5/NHSII!N4*PRODUCT(1+NHSII!D5:D12),2)} -> 1001.33 | S55: PSSRU 2024 and 2016
A56: 1 | B56: r_complaint_reduct | C56: =D56 -> 0.127 | D56: 0.127 | K56: intervention effect on complaints | L56: Reduction rate in complaints | M56: https://digital.nhs.uk/data-and-information/publications/statistical/data-on-written-complaints-in-the-nhs/2023-24 | N56: table 6 Data file of writeen complaints 2023/2024 showed that 12.7% complaints were due to communication. In the discussion/ explanation, we can explain that this is a conservative assumption, improved empathy can prevent complaints due to other reasons, for example: delayed diagnosis or medical error.

Sheet GP_base
A1: Input | B1: Value | C1: Not in use anymore
A2: smd_1 | B2: -0.5
A3: smd_2 | B3: -0.67
A4: smd_3 | B4: -0.63
A5: smd_sat | B5: 0.83
A6: n_patients_eligible | B6: =VLOOKUP(A6,GP_full!B:C,2,FALSE) -> 19255229
A7: p_subgroup1 | B7: =VLOOKUP(A7,GP_full!B:C,2,FALSE) -> 0.435
A8: p_subgroup2 | B8: =VLOOKUP(A8,GP_full!B:C,2,FALSE) -> 0.072
A9: p_subgroup3 | B9: =VLOOKUP(A9,GP_full!B:C,2,FALSE) -> 0.0838
A10: n_providers | B10: =VLOOKUP(A10,GP_full!B:C,2,FALSE) -> 28249
A11: v_threshold_1 | B11: =VLOOKUP(A11,GP_full!B:C,2,FALSE) -> 1
A12: v_threshold_2 | B12: =VLOOKUP(A12,GP_full!B:C,2,FALSE) -> 12
A13: v_threshold_3 | B13: =VLOOKUP(A13,GP_full!B:C,2,FALSE) -> 12
A14: v_mean_1_int
A15: v_mean_2_int
A16: v_mean_3_int
A17: v_mean_1_ctrl | B17: =VLOOKUP(A17,GP_full!B:C,2,FALSE) -> 2.5
A18: v_mean_2_ctrl | B18: =VLOOKUP(A18,GP_full!B:C,2,FALSE) -> 21.7
A19: v_mean_3_ctrl | B19: =VLOOKUP(A19,GP_full!B:C,2,FALSE) -> 27.9
A20: sd_1 | B20: =GP_full!E26 -> 0.809
A21: sd_2 | B21: =GP_full!E27 -> 13.331
A22: sd_3 | B22: =GP_full!E28 -> 14.566
A23: c_training_online | B23: =VLOOKUP(A23,GP_full!B:C,2,FALSE) -> 3.1
A24: c_training_f2f | B24: =VLOOKUP(A24,GP_full!B:C,2,FALSE) -> 14.6
A25: v_training_hours_online | B25: =VLOOKUP(A25,GP_full!B:C,2,FALSE) -> 5
A26: v_training_hours_f2f | B26: =VLOOKUP(A26,GP_full!B:C,2,FALSE) -> 7
A27: n_training_sessions | B27: 1
A28: c_opp_provider_hourly | B28: =VLOOKUP(A28,GP_full!B:C,2,FALSE) -> 161
A29: c_offset_1 | B29: =VLOOKUP(A29,GP_full!B:C,2,FALSE) -> 233
A30: c_offset_2 | B30: =VLOOKUP(A30,GP_full!B:C,2,FALSE) -> 7788
A31: c_offset_3 | B31: =VLOOKUP(A31,GP_full!B:C,2,FALSE) -> 13527
A32: c_care_component1_per_unit | B32: =VLOOKUP(A32,GP_full!B:C,2,FALSE) -> 4.47
A33: n_care_component1_units | B33: =VLOOKUP(A33,GP_full!B:C,2,FALSE) -> 2
A34: c_care_component2_per_unit | B34: =VLOOKUP(A34,GP_full!B:C,2,FALSE) -> NA
A35: n_care_component2_units | B35: =VLOOKUP(A35,GP_full!B:C,2,FALSE) -> NA
A36: p_satisfaction_int
A37: p_satisfaction_ctrl | B37: =VLOOKUP(A37,GP_full!B:C,2,FALSE) -> 0.713
A38: p_burnout_ctrl | B38: =VLOOKUP(A38,GP_full!B:C,2,FALSE) -> #N/A
A39: rr_burnout | B39: =VLOOKUP(A39,GP_full!B:C,2,FALSE) -> #N/A
A40: c_offset_burnout | B40: =VLOOKUP(A40,GP_full!B:C,2,FALSE) -> #N/A
A41: label_outcome_1 | B41: Pain
A42: label_outcome_2 | B42: Anxiety
A43: label_outcome_3 | B43: Depression

Sheet miscarriage_full
A1: For_R | B1: Input | C1: Value | D1: Mean | E1: SD | F1: DSA_low | G1: DSA_high | H1: PSA_dis | I1: PSA_param1 | J1: PSA_param2 | K1: Description | L1: Link | M1: Details from Ref | N1: Label_R | O1: Currency | P1: price_year_original | Q1: category_for_index | R1: value_inflated | S1: Source_index
K2: From a meta-analysis
A3: 1 | B3: smd_2 | C3: =D3 -> -0.63 | D3: -0.63 | E3: =(G3-C3)/1.96 -> 0.5 | F3: -1.61 | G3: 0.35 | H3: normal | I3: =C3 -> -0.63 | J3: =E3 -> 0.5 | K3: SMD_depression | M3: SMD=-0.63, 95%CI: -1.61, 0.35, N_intervention:548, N_control = 562 | N3: Effect size on depression
A4: 1 | B4: smd_sat | C4: =D4 -> 0.98 | D4: 0.98 | E4: =(G4-C4)/1.96 -> 0.26020408 | F4: 0.46 | G4: 1.49 | H4: normal | I4: =C4 -> 0.98 | J4: =E4 -> 0.26020408 | K4: SMD_satisfaction | M4: SMD=0.98, 95%CI: 0.46, 1.49. N_intervention:875, N_control = 619 | N4: Effect size on satisfaction
F5: 0.8 | G5: 1.2 | K5: From literature & calculation | L5: https://pmc.ncbi.nlm.nih.gov/articles/PMC11987160/ | M5: "Some maternity hospitals/units had dedicated RM clinics"
B6: n_patients_eligible | C6: =C7*C8 -> 107384.77 | D6: =ROUND(D8*D7,0) -> 107385 | K6: Number of women diagnosed with recurrent miscarriage, ﻿defined as at least 3 pregnancy losses | L6: https://obgyn.onlinelibrary.wiley.com/doi/10.1111/1471-0528.17515 | M6: Definition of recurrent miscarriage in the UK:3 or more pregnancy losses. Assuming 30% of woment with recurrent miscarriage seek for care annually
A7: 1 | B7: n_pt_compo1 | C7: =D7 -> 0.007 | D7: 0.007 | E7: =(G7-C7)/1.96 -> 0.00071428571 | F7: =C7*$F$5 -> 0.0056 | G7: =C7*$G$5 -> 0.0084 | H7: beta | I7: =C7*(((C7*(1-C7))/E7^2)-1) -> 95.36072 | J7: =(1-C7)*(((C7*(1-C7))/E7^2)-1) -> 13527.599 | K7: Prevalence of recurrent miscarriage | L7: https://www.sciencedirect.com/science/article/pii/S0140673621006826 | M7: The average population prevalence of women who have...three or more miscarriages is 0·7% (0·5–0·8%) | N7: Prevalence of recurrent miscarriage
A8: 1 | B8: n_pt_compo2 | C8: =D8 -> 15340682 | D8: 15340682 | F8: =C8 -> 15340682 | G8: =C8 -> 15340682 | K8: Total number of women aged 15-49 in the UK | L8: https://www.ons.gov.uk/peoplepopulationandcommunity/populationandmigration/populationestimates/datasets/populationestimatesforukenglandandwalesscotlandandnorthernireland | M8: Based on Mid-2023 dataset - sheet MYE2 - Females, the total number of women aged 15-49 = 15,340,682 | N8: Number of women aged 15-49
A9: 2 | B9: formula_n_patients | C9: =D9 -> n_pt_compo1*n_pt_compo2 | D9: n_pt_compo1*n_pt_compo2
B10: p_subgroup1 | C10: NA
B11: p_subgroup2 | C11: NA
B12: p_subgroup3 | C12: NA
B13: n_providers | D13: =ROUND(D8*D7*D14/D15,0) -> 165 | K13: Number of nurses specialized in recurrent miscarriage care | L13: Estimation | M13: Given the absence of standardized UK-specific data on case volumn of specialist nurse, we estimate the number of nurses as follow: estimated nurse's time per case = 2 hours, a full-time nurse band 5-6 works: 7.5 hours/day *209 days/year (table 11.2.2 PSSRU), 83% time for patient-related work (table 12.5.1)
A14: 1 | B14: n_provider_compo1 | C14: =D14 -> 2 | D14: 2 | E14: =(G14-C14)/1.96 -> 0.20408163 | F14: =C14*$F$5 -> 1.6 | G14: =C14*$G$5 -> 2.4 | H14: lognormal | I14: =LN(C14^2/SQRT(C14^2+E14^2)) -> 0.68796793 | J14: =SQRT(LN(1+E14^2/C14^2)) -> 0.10177668 | K14: Consultation duration (hours) | N14: Consultation duration
A15: 1 | B15: n_provider_compo2 | C15: =D15 -> 1301.025 | D15: =7.5*209*83% -> 1301.025 | E15: =(G15-C15)/1.96 -> 132.75765 | F15: =C15*$F$5 -> 1040.82 | G15: =C15*$G$5 -> 1561.23 | H15: lognormal | I15: =LN(C15^2/SQRT(C15^2+E15^2)) -> 7.1657284 | J15: =SQRT(LN(1+E15^2/C15^2)) -> 0.10177668 | K15: Annual working hours per nurse | L15: PSSRU | N15: Annual working hours/nurse
A16: 2 | B16: formula_n_providers | C16: =D16 -> (n_pt_compo1*n_pt_compo2)*n_provider_compo1/n_provider_compo2 | D16: (n_pt_compo1*n_pt_compo2)*n_provider_compo1/n_provider_compo2
A17: 1 | B17: v_threshold_1 | C17: =D17 -> 14 | D17: 14 | F17: =C17 -> 14 | G17: =C17 -> 14 | K17: Threshold of stress core based on Perceived Stress Scale | L17: https://pmc.ncbi.nlm.nih.gov/articles/PMC8896373/ | M17: "the recommended cut-off scores: 0–13 low stress; 14–26 moderate stress; 27–40 high stress.16" (ref 16 is not accessible) | N17: Stress threshold
A18: 1 | B18: v_threshold_2 | C18: =D18 -> 13 | D18: 13 | F18: =C18 -> 13 | G18: =C18 -> 13 | K18: Threshold of depression core based on EPDS | L18: https://www.bmj.com/content/371/bmj.m4022 | M18: A systematic review and meta-analysis concludes:"An EPDS cut-off value of 11 or higher maximised combined sensitivity and specificity; a cut-off value of 13 or higher was less sensitive but more specific. To identify pregnant and postpartum women with higher symptom levels, a cut-off of 13 or higher could be used." | N18: Depression threshold
B19: v_threshold_3 | C19: NA
A20: 1 | B20: v_mean_1_int | C20: =D20 -> 13.1 | D20: 13.1 | E20: 6.41 | F20: =C20-1.96*E20 -> 0.5364 | G20: =C20+1.96*E20 -> 25.6636 | H20: normal | I20: =C20 -> 13.1 | J20: =E20 -> 6.41 | K20: stress ﻿PSS post-test score of the population under empathic care | L20: Chang 2021 | M20: Table 2: experimental PSS posttest mean=13.1, sd=6.41 | N20: Stress score under intervention
B21: v_mean_2_int | D21: 7.77 | E21: 4.42 | F21: =C21-1.96*E21 -> -8.6632 | G21: =C21+1.96*E21 -> 8.6632 | K21: Post-test EPDS score of patients with depression under empathic care (only use this for scenario analysis) | L21: Chang 2021 | M21: Table 2: experimental SPDS posttest mean=7.77, sd=4.42
B22: v_mean_3_int | C22: NA
A23: 1 | B23: v_mean_1_ctrl | C23: =D23 -> 15.71 | D23: 15.71 | E23: 5.92 | F23: =C23-1.96*E23 -> 4.1068 | G23: =C23+1.96*E23 -> 27.3132 | H23: normal | I23: =C23 -> 15.71 | J23: =E23 -> 5.92 | K23: Stress ﻿PSS post-test score of the population under standard of care | L23: Chang 2021 | M23: Table 2: Control PSS posttest mean=15.71, sd=5.92 | N23: Stress score under usual care
A24: 1 | B24: v_mean_2_ctrl | C24: =D24 -> 8.79 | D24: 8.79 | E24: 4.86 | F24: =C24-1.96*E24 -> -0.7356 | G24: =C24+1.96*E24 -> 18.3156 | H24: normal | I24: =C24 -> 8.79 | J24: =E24 -> 4.86 | K24: Depression EPDS post-test score of patients under standard of care | L24: Chang 2021 | M24: Table 2: Control SPDS posttest mean=8.79, sd=4.86 | N24: Depression score under usual care
B25: v_mean_3_ctrl | C25: NA
A26: 1 | B26: sd_1 | C26: =D26 -> 5.92 | D26: =E23 -> 5.92 | F26: =C26*$F$5 -> 4.736 | G26: =C26*$G$5 -> 7.104 | N26: Standard deviation - stress
A27: 1 | B27: sd_2 | C27: =D27 -> 4.86 | D27: =E24 -> 4.86 | F27: =C27*$F$5 -> 3.888 | G27: =C27*$G$5 -> 5.832 | N27: Standard deviation - depresssion
B28: sd_3 | C28: NA
A29: 1 | B29: c_training_online | C29: =D29 -> 3.1 | D29: 3.1 | E29: =(G29-C29)/1.96 -> 0.31632653 | F29: =C29*$F$5 -> 2.48 | G29: =C29*$G$5 -> 3.72 | H29: gamma | I29: =C29^2/E29^2 -> 96.04 | J29: =E29^2/C29 -> 0.032278217 | K29: Cost of online training per nurse | M29: Expert facilitator (1): 200; Training for facilitator: 10; Admin support (1/2 day): 100; Resources 0; Lunch + refreshments 0; Total_cost: 310 Cost per HCP: 3.1 | N29: Training online cost
A30: 1 | B30: c_training_f2f | C30: =D30 -> 14.6 | D30: 14.6 | E30: =(G30-C30)/1.96 -> 1.4897959 | F30: =C30*$F$5 -> 11.68 | G30: =C30*$G$5 -> 17.52 | H30: gamma | I30: =C30^2/E30^2 -> 96.04 | J30: =E30^2/C30 -> 0.15201999 | K30: Cost of f2f training per nurse | M30: Expert facilitator (1): 200; Training for facilitator: 10; Admin support (1/2 day): 100; Resources 50; Lunch + refreshments 1000; Total_cost: 1460 Cost per HCP: 14.6 | N30: Training offline cost
A31: 1 | B31: v_training_hours_online | C31: =D31 -> 5 | D31: 5 | N31: Training online duration
A32: 1 | B32: v_training_hours_f2f | C32: =D32 -> 7 | D32: 7 | N32: Training offline duration
A33: 1 | B33: n_training_sessions | C33: =D33 -> 1 | D33: 1 | N33: Number of training sessions
A34: 1 | B34: c_opp_provider_hourly | C34: =D34 -> 52 | D34: 52 | E34: =(G34-C34)/1.96 -> 5.3061224 | F34: =C34*$F$5 -> 41.6 | G34: =C34*$G$5 -> 62.4 | H34: gamma | I34: =C34^2/E34^2 -> 96.04 | J34: =E34^2/C34 -> 0.54144107 | K34: Opportunity cost of nurses (taking the training course instead of working) | L34: PSSRU | M34: ﻿Table 11.2.2: Annual and unit costs for hospital-based nurses. ﻿Cost per hour (including qualifications) Band 5: ﻿£52 for basecase, DSA range: band 4- band 7: ﻿£43-73 | N34: Opportunity cost of nurse
A35: 1 | B35: c_offset_1 | C35: =D35 -> 0 | D35: 0 | F35: 0 | G35: 100 | K35: Cost associated with reduced stress per patient | L35: https://eprints.lse.ac.uk/59885/1/__lse.ac.uk_storage_LIBRARY_Secondary_libfile_shared_repository_Content_Bauer%2C%20M_Bauer_Costs_perinatal_%20mental_2014_Bauer_Costs_perinatal_mental_2014_author.pdf | M35: This document did not confirm that stress doesn't cost money, but cost of stress wasn't mentioned while cost of other conditions were. Nigel agreed with this assumption and suggest to mention this conservative assumption in the discussion | N35: Saving from reduced stress per patient
D36: =GP_full!D43 -> 6478.6 | L36: https://pubmed.ncbi.nlm.nih.gov/25031113/ | M36: "﻿Hypothesis tests of the PSS consistently demonstrated a satisfactory correlation with depression or anxiety" but correlation doesn't mean equal. Moreover, cost of anxiety is larger than cost of recurrent miscarriage which consists of medical and psychological care => over estimate
A37: 1 | B37: c_offset_2 | C37: =R37 -> 2158.6 | D37: 1688 | E37: =(G37-C37)/1.96 -> 220.26531 | F37: =C37*$F$5 -> 1726.88 | G37: =C37*$G$5 -> 2590.32 | H37: gamma | I37: =C37^2/E37^2 -> 96.04 | J37: =E37^2/C37 -> 22.476052 | K37: Cost associated with improved depression per patient | L37: https://eprints.lse.ac.uk/59885/1/__lse.ac.uk_storage_LIBRARY_Secondary_libfile_shared_repository_Content_Bauer%2C%20M_Bauer_Costs_perinatal_%20mental_2014_Bauer_Costs_perinatal_mental_2014_author.pdf | M37: Costs of perinatal depression 1,688 pounds per case (2014, table 1) | N37: Saving from reduced depression per patient | O37: £ | P37: 2014 | Q37: NHSII pay and prices | R37: {=ROUND(D37*PRODUCT(1+NHSII!D4:D12)*(1+NHSII!J9/100),2)} -> 2158.6 | S37: PSSRU 2024 and 2020
B38: c_offset_3
A39: 1 | B39: c_care_component1_per_unit | C39: =D40 -> 52 | D39: 200 | E39: =(G39-C39)/1.96 -> 5.3061224 | F39: =C39*$F$5 -> 41.6 | G39: =C39*$G$5 -> 62.4 | H39: gamma | I39: =C39^2/E39^2 -> 96.04 | J39: =E39^2/C39 -> 0.54144107 | K39: Cost of a consultation session | L39: https://www.p4fertility.co.uk/services/recurrent-miscarriage | M39: No NHS cost is available. Private cost is around 200 | N39: Consultation fee
D40: 52 | L40: Assumption | M40: Assuming each consultation section lasts for 1 hour, the cost of the consultation = nurse wage per hour
A41: 1 | B41: n_care_component1_units | C41: =D41 -> 3 | D41: 3 | K41: Number of extra consultation sessions | L41: Chang 2021 | M41: "﻿Face-to-face counseling interventions were offered at 1, 5, and 12 weeks after enrollment" | N41: Extra consultation sessions
B42: c_care_component2_per_unit | C42: NA
B43: n_care_component2_units | C43: NA
B44: p_satisfaction_int | D44: =_xlfn.NORM.S.DIST(_xlfn.NORM.S.INV(D45)+D4,TRUE) -> 0.87096598 | K44: Proportion of patients satisfied with the empathic care at GP | L44: Calculation | M44: In the control group, we assume the underlying satisfaction tendency follows N(0,1). The SMD shifts the mean of this distribution, and the resulting cumulative probability gives the intervention group’s expected satisfaction rate.
A45: 1 | B45: p_satisfaction_ctrl | C45: =D45 -> 0.56 | D45: 0.56 | E45: =(G45-C45)/1.96 -> 0.057142857 | F45: =C45*$F$5 -> 0.448 | G45: =C45*$G$5 -> 0.672 | H45: beta | I45: =C45*(((C45*(1-C45))/E45^2)-1) -> 41.6976 | J45: =(1-C45)*(((C45*(1-C45))/E45^2)-1) -> 32.7624 | K45: Proportion of patients satisfied with the standard of care of nurses | L45: https://pmc.ncbi.nlm.nih.gov/articles/PMC10064661/#Sec12 | M45: Fig 1: answer to the question "How would you eate your experience of the care you received for RM?" 44% poor, 39% satisfactory, 17% good | N45: Satisfaction rate under usual care
A46: 1 | B46: d_absent_per_hcp | C46: =ROUND(D46,2) -> 4.51 | D46: =1567605/347385 -> 4.5125869 | K46: Number of absent days due to burnout among nurses annually | L46: IPPO report (ref 42 burnout | M46: Table 3: Days absent due to mental health, in Nurses: ﻿1,567,605; number of Nurses: ﻿﻿347,385 | N46: Days absent per GP
A47: 1 | B47: c_hcp_day_rate | C47: =R47 -> 182.58 | D47: 157.38 | K47: Cost of an absent day | L47: IPPO report (ref 42 burnout | M47: Table 3: FTE daily rate of Nurses | N47: Day wage per GP | O47: £ | P47: 2022 | Q47: NHSII pay | R47: {=ROUND(D47*PRODUCT(1+NHSII!C10:C12),2)} -> 182.58 | S47: PSSRU 2024
A48: 1 | B48: r_absent_reduct | C48: =D48 -> 0.1 | D48: 0.1 | K48: Percentage reduction in absent days due to the intervention | L48: Assumption | N48: Reduction rate in absent days under intervention
A49: 1 | B49: n_complaints | C49: =D49 -> 75.954382 | D49: =GP_full!D54/GP_full!D9*miscarriage_full!D6 -> 75.954382 | K49: estimated number of complaints in recurrent miscarriage care | L49: Assumption | M49: There is no data on the number of complaints occur in clinics or maternity unit related to recurrent miscarriage care. We applied the proportion of complaints among total GP consultations in this case: N_complaints_nurses = N_complaints_GP/N_consultations*N_patients_miscarriage
A50: 1 | B50: c_complaint | C50: =R50 -> 1001.33 | D50: 667.17 | E50: =(G50-C50)/1.96 -> 102.17653 | F50: =C50*$F$5 -> 801.064 | G50: =C50*$G$5 -> 1201.596 | H50: gamma | I50: =C50^2/E50^2 -> 96.04 | J50: =E50^2/C50 -> 10.426177 | K50: Cost associated with reducing one complaint | L50: PSSRU | M50: "﻿﻿﻿In 2006-07, The estimated cost of handling and review of NHS complaints was £89 million" "﻿The NHS Received 133,400 written complaints" => cost per complaint: =89e6/133400=677 | N50: Saving from reduced one complaint | O50: £ | P50: 2006 | Q50: NHSII pay and prices | R50: {=ROUND(D50*NHSII!N5/NHSII!N4*PRODUCT(1+NHSII!D5:D12),2)} -> 1001.33 | S50: PSSRU 2024 and 2016
A51: 1 | B51: r_complaint_reduct | C51: =D51 -> 0.171 | D51: 0.171 | K51: intervention effect on complaints | L51: https://digital.nhs.uk/data-and-information/publications/statistical/data-on-written-complaints-in-the-nhs/2023-24 | M51: table 3 Data file of writeen complaints 2023/2024 in NHS Hospital and Community Health Services showed that 17.1% complaints were due to communication | N51: Reduction rate in complaints

Sheet NHSII
A1: ﻿Annual % increases on the previous year | D1: PSSRU 2024 | G1: HCHS/NHS inflators all sectors | J1: PSSRU 2020 | N1: PSSRU 2016
A2: (NHS Providers) | G2: Annual % increases on previous year
B3: NHSCII prices | C3: NHSCII pay | D3: NHSCII pay and prices | G3: Year | H3: HCHS prices | I3: HCHS pay | J3: HCHS pay and prices | M3: Year | N3: pay and prices index
A4: 2015/2016 | B4: 0.0056 | C4: 0.003 | D4: 0.004 | G4: 2009/2010 | H4: -1.3 | I4: 1.8 | J4: 0.6 | M4: 2006/07 | N4: 249.8
A5: 2016/2017 | B5: 0.0206 | C5: 0.021 | D5: 0.0209 | G5: 2010/2011 | H5: 2.8 | I5: 3.1 | J5: 3 | M5: 2015/16 | N5: 297
A6: 2017/2018 | B6: 0.013 | C6: 0.0121 | D6: 0.0124 | G6: 2011/2012 | H6: 4.1 | I6: 0.9 | J6: 2.1
A7: 2018/2019 | B7: 0.0159 | C7: 0.016 | D7: 0.016 | G7: 2012/2013 | H7: 3.1 | I7: 0.9 | J7: 1.7
A8: 2019/2020 | B8: 0.013 | C8: 0.0258 | D8: 0.0214 | G8: 2013/2014 | H8: 1.8 | I8: 0.7 | J8: 1.1
A9: 2020/2021 | B9: 0.0084 | C9: 0.0341 | D9: 0.0249 | G9: 2014/2015 | H9: 1.7 | I9: 0.3 | J9: 0.9
A10: 2021/2022 | B10: 0.0172 | C10: 0.0307 | D10: 0.0258 | G10: 2015/2016 | H10: 2.7 | I10: 0.3 | J10: 1.3
A11: 2022/2023 | B11: 0.0715 | C11: 0.0741 | D11: 0.0732
A12: 2023/2024* | B12: 0.0345 | C12: 0.0479 | D12: 0.0431
